[
  {
    "id": 1,
    "firstname": "John",
    "lastname": "Doe",
    "email": "john.doe@example.com",
    "age": 30
  },
  {
    "id": 2,
    "firstname": "Jane",
    "lastname": "Smith",
    "email": "jane.smith@example.com",
    "age": 28
  },
  {
    "id": 3,
    "firstname": "Alice",
    "lastname": "Johnson",
    "email": "alice.johnson@example.com",
    "age": 35
  },
  {
    "id": 4,
    "firstname": "Bob",
    "lastname": "Brown",
    "email": "bob.brown@example.com",
    "age": 40
  },
  {
    "id": 5,
    "firstname": "Charlie",
    "lastname": "Davis",
    "email": "charlie.davis@example.com",
    "age": 22
  },
  {
    "id": 6,
    "firstname": "David",
    "lastname": "Evans",
    "email": "david.evans@example.com",
    "age": 32
  },
  {
    "id": 7,
    "firstname": "Emma",
    "lastname": "Wilson",
    "email": "emma.wilson@example.com",
    "age": 26
  },
  {
    "id": 8,
    "firstname": "Frank",
    "lastname": "Miller",
    "email": "frank.miller@example.com",
    "age": 45
  },
  {
    "id": 9,
    "firstname": "Grace",
    "lastname": "Lee",
    "email": "grace.lee@example.com",
    "age": 29
  },
  {
    "id": 10,
    "firstname": "Henry",
    "lastname": "Thompson",
    "email": "henry.thompson@example.com",
    "age": 38
  },
  {
    "id": 11,
    "firstname": "Irene",
    "lastname": "Garcia",
    "email": "irene.garcia@example.com",
    "age": 27
  },
  {
    "id": 12,
    "firstname": "Jack",
    "lastname": "Martinez",
    "email": "jack.martinez@example.com",
    "age": 31
  },
  {
    "id": 13,
    "firstname": "Karen",
    "lastname": "Rodriguez",
    "email": "karen.rodriguez@example.com",
    "age": 33
  },
  {
    "id": 14,
    "firstname": "Liam",
    "lastname": "Harris",
    "email": "liam.harris@example.com",
    "age": 24
  },
  {
    "id": 15,
    "firstname": "Mia",
    "lastname": "Clark",
    "email": "mia.clark@example.com",
    "age": 30
  },
  {
    "id": 16,
    "firstname": "Noah",
    "lastname": "Lewis",
    "email": "noah.lewis@example.com",
    "age": 34
  },
  {
    "id": 17,
    "firstname": "Olivia",
    "lastname": "Walker",
    "email": "olivia.walker@example.com",
    "age": 28
  },
  {
    "id": 18,
    "firstname": "Paul",
    "lastname": "Young",
    "email": "paul.young@example.com",
    "age": 41
  },
  {
    "id": 19,
    "firstname": "Quinn",
    "lastname": "Allen",
    "email": "quinn.allen@example.com",
    "age": 23
  },
  {
    "id": 20,
    "firstname": "Rachel",
    "lastname": "King",
    "email": "rachel.king@example.com",
    "age": 36
  }
]
